ipyrhinoviewer/__init__.py
ipyrhinoviewer/_frontend.py
ipyrhinoviewer/_version.py
ipyrhinoviewer/widget.py
ipyrhinoviewer/labextension/build_log.json
ipyrhinoviewer/labextension/package.json
ipyrhinoviewer/labextension/static/lib_index_js.92eddff79f74d5505351.js
ipyrhinoviewer/labextension/static/lib_index_js.92eddff79f74d5505351.js.map
ipyrhinoviewer/labextension/static/lib_plugin_js.ab462a0f63f9e4353b94.js
ipyrhinoviewer/labextension/static/lib_plugin_js.ab462a0f63f9e4353b94.js.map
ipyrhinoviewer/labextension/static/lib_widget_js-webpack_sharing_consume_default_three_three.31baad537f8b71b3412b.js
ipyrhinoviewer/labextension/static/lib_widget_js-webpack_sharing_consume_default_three_three.31baad537f8b71b3412b.js.map
ipyrhinoviewer/labextension/static/lib_widget_js-webpack_sharing_consume_default_three_three.c9bb58408adfe2a820f6.js
ipyrhinoviewer/labextension/static/lib_widget_js-webpack_sharing_consume_default_three_three.c9bb58408adfe2a820f6.js.map
ipyrhinoviewer/labextension/static/remoteEntry.c27ac238a51250549bb2.js.map
ipyrhinoviewer/labextension/static/remoteEntry.ec0d0b913e46bab5d25d.js
ipyrhinoviewer/labextension/static/remoteEntry.ec0d0b913e46bab5d25d.js.map
ipyrhinoviewer/labextension/static/style.js
ipyrhinoviewer/labextension/static/vendors-node_modules_css-loader_dist_runtime_api_js-node_modules_style-loader_dist_runtime_in-1ad0a7.57d1ecec4240c7675ee8.js
ipyrhinoviewer/labextension/static/vendors-node_modules_css-loader_dist_runtime_api_js-node_modules_style-loader_dist_runtime_in-1ad0a7.57d1ecec4240c7675ee8.js.map
ipyrhinoviewer/labextension/static/vendors-node_modules_three_build_three_module_js.1bcd852ef0383f1699ac.js
ipyrhinoviewer/labextension/static/vendors-node_modules_three_build_three_module_js.1bcd852ef0383f1699ac.js.map
ipyrhinoviewer/nbextension/extension.js
ipyrhinoviewer/nbextension/index.js
ipyrhinoviewer/nbextension/index.js.LICENSE.txt
ipyrhinoviewer/nbextension/index.js.map
ipyrhinoviewer/tests/__init__.py
ipyrhinoviewer-0.2.6.dist-info/LICENSE.txt
ipyrhinoviewer-0.2.6.dist-info/METADATA
ipyrhinoviewer-0.2.6.dist-info/WHEEL
ipyrhinoviewer-0.2.6.dist-info/top_level.txt
ipyrhinoviewer-0.2.6.dist-info/RECORD
